Cepheus/__init__.py
Cepheus-1.0.1.dist-info/DESCRIPTION.rst
Cepheus-1.0.1.dist-info/METADATA
Cepheus-1.0.1.dist-info/RECORD
Cepheus-1.0.1.dist-info/WHEEL
Cepheus-1.0.1.dist-info/metadata.json
Cepheus-1.0.1.dist-info/top_level.txt
