Metadata-Version: 2.0
Name: Cepheus
Version: 1.0.1
Summary: Cepheus, son of Agenor. A program to analyze cepheid variable stars.
Home-page: https://github.com/nicklayden/Cepheus
Author: Nicholas Layden
Author-email: nicholas.layden@gmail.com
License: GNU
Keywords: Astronomy,variables,cepheids
Platform: UNKNOWN
Classifier: Development Status :: 3 - Alpha
Classifier: Intended Audience :: Developers
Classifier: Topic :: Software Development :: Documentation
Classifier: Topic :: Documentation
Classifier: Topic :: Utilities
Classifier: License :: OSI Approved :: GNU General Public License v3 (GPLv3)
Classifier: Programming Language :: Python
Classifier: Programming Language :: Python :: 2
Classifier: Programming Language :: Python :: 2.7
Classifier: Programming Language :: Python :: 3
Classifier: Programming Language :: Python :: 3.3
Classifier: Programming Language :: Python :: 3.4
Requires-Dist: WCSAxes
Requires-Dist: astropy
Requires-Dist: beautifulsoup4
Requires-Dist: photutils
